konesyntees/__init__.py
konesyntees/konesyntees.py
konesyntees-0.1.0.dist-info/LICENSE
konesyntees-0.1.0.dist-info/METADATA
konesyntees-0.1.0.dist-info/WHEEL
konesyntees-0.1.0.dist-info/top_level.txt
konesyntees-0.1.0.dist-info/RECORD
