Metadata-Version: 2.1
Name: konesyntees
Version: 0.1.0
Summary: Python client for the voice synthesis service by the Institute of the Estonian Language.
Home-page: https://github.com/madeline-bot/konesyntees.py
Author: Dennys Matthew
Author-email: git@gnztmpz.eu.org
License: MIT license
Keywords: konesyntees
Classifier: Development Status :: 2 - Pre-Alpha
Classifier: Intended Audience :: Developers
Classifier: License :: OSI Approved :: MIT License
Classifier: Natural Language :: English
Classifier: Programming Language :: Python :: 3
Classifier: Programming Language :: Python :: 3.6
Classifier: Programming Language :: Python :: 3.7
Classifier: Programming Language :: Python :: 3.8
Requires-Python: >=3.6
License-File: LICENSE
Requires-Dist: cloudscraper
Requires-Dist: requests
Requires-Dist: requests-toolbelt
